source/Xnat.py
source/__init__.py
source/conf.py
source/util.py
xnatum/Xnat.py
xnatum/__init__.py
xnatum/conf.py
xnatum/util.py
xnatum-1.2.dist-info/METADATA
xnatum-1.2.dist-info/RECORD
xnatum-1.2.dist-info/WHEEL
xnatum-1.2.dist-info/top_level.txt
