Metadata-Version: 2.1
Name: xnatum
Version: 1.2
Summary: A package for connecting and manage data on XNAT.
Home-page: https://github.com/rgllm/xnatum
Author: Rogerio Moreira
Author-email: r@rgllm.com
License: MIT
Platform: UNKNOWN
Requires-Dist: xnat
Requires-Dist: dicom2nifti
